replot/__init__.py
replot/__main__.py
replot/dependencies.py
replot/metadata.py
replot/patch.py
replot/utils.py
replot-0.1.4.dist-info/LICENSE
replot-0.1.4.dist-info/WHEEL
replot-0.1.4.dist-info/METADATA
replot-0.1.4.dist-info/RECORD
