Metadata-Version: 2.1
Name: replot
Version: 0.1.4
Summary: How did I create that plot again 🤔
Author: Dominik1123
Requires-Python: >=3.7
Classifier: License :: OSI Approved :: MIT License
Requires-Dist: matplotlib >= 3.0
Requires-Dist: Pillow >= 8.0
Requires-Dist: GitPython >= 3.0
Project-URL: Home, https://github.com/Dominik1123/re-plot
Project-URL: Source, https://github.com/Dominik1123/re-plot
